wyoming_porcupine1/__init__.py
wyoming_porcupine1/__main__.py
wyoming_porcupine1/data/lib/common/porcupine_params_de.pv
wyoming_porcupine1/data/lib/common/porcupine_params_en.pv
wyoming_porcupine1/data/lib/common/porcupine_params_es.pv
wyoming_porcupine1/data/lib/common/porcupine_params_fr.pv
wyoming_porcupine1/data/resources/de/linux/ananas_linux.ppn
wyoming_porcupine1/data/resources/de/linux/heuschrecke_linux.ppn
wyoming_porcupine1/data/resources/de/linux/himbeere_linux.ppn
wyoming_porcupine1/data/resources/de/linux/leguan_linux.ppn
wyoming_porcupine1/data/resources/de/linux/stachelschwein_linux.ppn
wyoming_porcupine1/data/resources/de/raspberry-pi/ananas_raspberry-pi.ppn
wyoming_porcupine1/data/resources/de/raspberry-pi/heuschrecke_raspberry-pi.ppn
wyoming_porcupine1/data/resources/de/raspberry-pi/himbeere_raspberry-pi.ppn
wyoming_porcupine1/data/resources/de/raspberry-pi/leguan_raspberry-pi.ppn
wyoming_porcupine1/data/resources/de/raspberry-pi/stachelschwein_raspberry-pi.ppn
wyoming_porcupine1/data/resources/en/linux/alexa_linux.ppn
wyoming_porcupine1/data/resources/en/linux/americano_linux.ppn
wyoming_porcupine1/data/resources/en/linux/blueberry_linux.ppn
wyoming_porcupine1/data/resources/en/linux/bumblebee_linux.ppn
wyoming_porcupine1/data/resources/en/linux/computer_linux.ppn
wyoming_porcupine1/data/resources/en/linux/grapefruit_linux.ppn
wyoming_porcupine1/data/resources/en/linux/grasshopper_linux.ppn
wyoming_porcupine1/data/resources/en/linux/hey google_linux.ppn
wyoming_porcupine1/data/resources/en/linux/hey siri_linux.ppn
wyoming_porcupine1/data/resources/en/linux/jarvis_linux.ppn
wyoming_porcupine1/data/resources/en/linux/ok google_linux.ppn
wyoming_porcupine1/data/resources/en/linux/pico clock_linux.ppn
wyoming_porcupine1/data/resources/en/linux/picovoice_linux.ppn
wyoming_porcupine1/data/resources/en/linux/porcupine_linux.ppn
wyoming_porcupine1/data/resources/en/linux/smart mirror_linux.ppn
wyoming_porcupine1/data/resources/en/linux/snowboy_linux.ppn
wyoming_porcupine1-1.0.1.dist-info/LICENSE.md
wyoming_porcupine1-1.0.1.dist-info/METADATA
wyoming_porcupine1-1.0.1.dist-info/WHEEL
wyoming_porcupine1-1.0.1.dist-info/top_level.txt
wyoming_porcupine1-1.0.1.dist-info/RECORD
