Metadata-Version: 2.1
Name: wyoming-porcupine1
Version: 1.0.1
Summary: Wyoming Server for Porcupine 1
Home-page: http://github.com/rhasspy/wyoming-porcupine1
Author: Michael Hansen
Author-email: mike@rhasspy.org
License: MIT
Keywords: rhasspy wyoming porcupine wake word
Classifier: Development Status :: 3 - Alpha
Classifier: Intended Audience :: Developers
Classifier: Topic :: Text Processing :: Linguistic
Classifier: License :: OSI Approved :: MIT License
Classifier: Programming Language :: Python :: 3.7
Classifier: Programming Language :: Python :: 3.8
Classifier: Programming Language :: Python :: 3.9
Classifier: Programming Language :: Python :: 3.10
Classifier: Programming Language :: Python :: 3.11
License-File: LICENSE.md
Requires-Dist: pvporcupine ~=1.9.0
Requires-Dist: wyoming ==1.2.0
